corun.py
setup.py
corun.egg-info/PKG-INFO
corun.egg-info/SOURCES.txt
corun.egg-info/dependency_links.txt
corun.egg-info/requires.txt
corun.egg-info/top_level.txt