Metadata-Version: 1.0
Name: corun
Version: 0.1.0
Summary: coroutine library
Home-page: UNKNOWN
Author: Rodney Gomes
Author-email: rodneygomes@gmail.com
License: Apache 2.0 License
Keywords: coroutine
Platform: UNKNOWN
